Metadata-Version: 2.4
Name: pyscf-sidereus
Version: 0.5.1
Summary: SIDEREUS module for PySCF - Enhanced quantum chemistry calculations
Author-email: Yijie Xia <yijiexia@pku.edu.cn>
License: Apache-2.0
Classifier: Development Status :: 3 - Alpha
Classifier: Intended Audience :: Science/Research
Classifier: License :: OSI Approved :: Apache Software License
Classifier: Natural Language :: English
Classifier: Operating System :: POSIX
Classifier: Programming Language :: Python :: 3
Classifier: Topic :: Software Development :: Libraries :: Python Modules
Classifier: Topic :: Scientific/Engineering :: Physics
Classifier: Topic :: Scientific/Engineering :: Chemistry
Requires-Dist: pyscf
Requires-Dist: numpy==1.26.4
Requires-Dist: rdkit
Requires-Dist: matplotlib
Requires-Dist: pyyaml
Requires-Dist: pysisyphus
